SyloraQAPI/__init__.py
SyloraQAPI/module.py
syloraqapi-0.2.dist-info/LICENSE
syloraqapi-0.2.dist-info/METADATA
syloraqapi-0.2.dist-info/WHEEL
syloraqapi-0.2.dist-info/top_level.txt
syloraqapi-0.2.dist-info/RECORD
