Metadata-Version: 2.2
Name: SyloraQAPI
Version: 0.2
Summary: SyloraQ Python Module One Step Ahead
Home-page: https://github.com/SyloraQ/SyloraQ
Author: SyloraQ
Author-email: syloraq.official@gmail.com
Classifier: Programming Language :: Python :: 3
Classifier: License :: OSI Approved :: MIT License
Classifier: Intended Audience :: Developers
License-File: LICENSE
Dynamic: author
Dynamic: author-email
Dynamic: classifier
Dynamic: description
Dynamic: description-content-type
Dynamic: home-page
Dynamic: summary
